foamgraph/__init__.py
foamgraph/aesthetics.py
foamgraph/algorithm.py
foamgraph/config.py
foamgraph/graphics_scene.py
foamgraph/live_window.py
foamgraph/utility.py
foamgraph/version.py
foamgraph/backend/__init__.py
foamgraph/backend/QtCore/__init__.py
foamgraph/backend/QtGui/__init__.py
foamgraph/backend/QtTest/__init__.py
foamgraph/backend/QtWidgets/__init__.py
foamgraph/ctrl_widgets/__init__.py
foamgraph/ctrl_widgets/base_ctrl_widgets.py
foamgraph/ctrl_widgets/smart_widgets.py
foamgraph/data_model/__init__.py
foamgraph/data_model/data_item_base.py
foamgraph/data_model/roi_data_item.py
foamgraph/graph_view/__init__.py
foamgraph/graph_view/graph_view.py
foamgraph/graph_view/graphics_view.py
foamgraph/graph_view/image_view.py
foamgraph/graph_view/smart_view.py
foamgraph/graph_view/test/__init__.py
foamgraph/graph_view/test/test_graph_view.py
foamgraph/graph_view/test/test_image_view.py
foamgraph/graph_view/test/test_smart_view.py
foamgraph/graphics_item/__init__.py
foamgraph/graphics_item/arrow_item.py
foamgraph/graphics_item/graphics_item.py
foamgraph/graphics_item/image_item.py
foamgraph/graphics_item/line_item.py
foamgraph/graphics_item/linear_region_item.py
foamgraph/graphics_item/mouse_cursor_item.py
foamgraph/graphics_item/region_of_interest_item.py
foamgraph/graphics_item/plot_item/__init__.py
foamgraph/graphics_item/plot_item/annotation_item.py
foamgraph/graphics_item/plot_item/bar_plot_item.py
foamgraph/graphics_item/plot_item/candlestick_plot_item.py
foamgraph/graphics_item/plot_item/curve_plot_item.py
foamgraph/graphics_item/plot_item/errorbar_plot_item.py
foamgraph/graphics_item/plot_item/plot_item.py
foamgraph/graphics_item/plot_item/scatter_plot_item.py
foamgraph/graphics_item/plot_item/shaded_plot_item.py
foamgraph/graphics_item/plot_item/stem_plot_item.py
foamgraph/graphics_item/plot_item/test/__init__.py
foamgraph/graphics_item/plot_item/test/conftest.py
foamgraph/graphics_item/plot_item/test/test_annotation_item.py
foamgraph-0.2.4.dist-info/LICENSE
foamgraph-0.2.4.dist-info/METADATA
foamgraph-0.2.4.dist-info/WHEEL
foamgraph-0.2.4.dist-info/top_level.txt
foamgraph-0.2.4.dist-info/RECORD
