Metadata-Version: 2.1
Name: foamgraph
Version: 0.2.4
Summary: Fast visualization library for interactive online analysis at scientific user facilities
Author-email: Jun Zhu <zhujun981661@gmail.com>
License: BSD 3-Clause License
Project-URL: repository, https://github.com/zhujun98/foamgraph
Classifier: Development Status :: 4 - Beta
Classifier: Intended Audience :: Developers
Classifier: License :: OSI Approved :: BSD License
Classifier: Operating System :: OS Independent
Classifier: Programming Language :: Python :: 3.9
Classifier: Programming Language :: Python :: 3.10
Classifier: Topic :: Scientific/Engineering :: Visualization
Requires-Python: >=3.9
License-File: LICENSE
Requires-Dist: numpy (>=1.21.5)
Provides-Extra: test
Requires-Dist: pytest ; extra == 'test'
Requires-Dist: pytest-qt ; extra == 'test'
Requires-Dist: pytest-cov ; extra == 'test'
